{
 "dependencies":{
  "async":{
   "version":"3.2.6"
  },
  "chalk":{
   "version":"5.6.0"
  },
  "fs-extra":{
   "version":"10.1.0"
  },
  "glob":{
   "version":"10.3.6"
  },
  "istanbul":{
   "version":"0.4.5"
  },
  "lodash":{
   "version":"4.17.21"
  },
  "uglify-js":{
   "version":"3.17.4"
  },
  "webpack":{
   "version":"5.97.1"
  }
 },
 "lockfileVersion":2,
 "name":"lodash",
 "packages":{
  "":{
   "name":"lodash",
   "version":"4.17.23"
  },
  "/usr/share/nodejs/async":{
   "name":"async",
   "version":"3.2.6"
  },
  "/usr/share/nodejs/chalk":{
   "name":"chalk",
   "version":"5.6.0"
  },
  "/usr/share/nodejs/fs-extra":{
   "name":"fs-extra",
   "version":"10.1.0"
  },
  "/usr/share/nodejs/glob":{
   "name":"glob",
   "version":"10.3.6"
  },
  "/usr/share/nodejs/istanbul":{
   "name":"istanbul",
   "version":"0.4.5"
  },
  "/usr/share/nodejs/lodash":{
   "name":"lodash",
   "version":"4.17.21"
  },
  "/usr/share/nodejs/uglify-js":{
   "name":"uglify-js",
   "version":"3.17.4"
  },
  "/usr/share/nodejs/webpack":{
   "name":"webpack",
   "version":"5.97.1"
  }
 },
 "pkgjs_version":"0.17.1",
 "version":"4.17.23"
}